scors-0.2.3.dist-info/METADATA
scors-0.2.3.dist-info/WHEEL
scors-0.2.3.dist-info/licenses/LICENSE
scors/__init__.py
scors/_scors.pypy311-pp73-aarch64-linux-gnu.so
scors-0.2.3.dist-info/RECORD
