Metadata-Version: 2.4
Name: scors
Version: 0.2.3
License-File: LICENSE
Summary: Binary classification scores in Rust
Home-Page: https://github.com/hanslovsky/scors
Author-email: Philipp Hanslovsky <philipp.hanslovsky@gmail.com>
Maintainer-email: Philipp Hanslovsky <philipp.hanslovsky@gmail.com>
License-Expression: MIT
Requires-Python: >=3.10, <3.13
Project-URL: Homepage, https://github.com/hanslovsky/scors
Project-URL: Documentation, https://github.com/hanslovsky/scors
Project-URL: Repository, https://github.com/hanslovsky/scors
Project-URL: Issues, https://github.com/hanslovsky/scors/issues
